<?xml version="1.0" encoding="UTF-8" standalone="no"?>
<BlockMap xmlns="http://schemas.microsoft.com/appx/2010/blockmap" HashMethod="http://www.w3.org/2001/04/xmlenc#sha256"><File Name="manifest.xml" Size="5030" LfhSize="42"><Block Hash="o+TVBTJUYX9cuqVUUqsm8FWcAuni1wa+SMmOkKlqPCM=" Size="1085"/></File><File Name="win32\index.html" Size="10933" LfhSize="46"><Block Hash="4geUVBjwE18eJo6n8eex/bVL8IGMJXA52xwA79w5rL8=" Size="5003"/></File><File Name="icon-32.png" Size="439" LfhSize="41"><Block Hash="B4hJk3t4s9KREWd1gdeEIPG8Zum6gacuY+NYBLc9yj8="/></File><File Name="AppxManifest.xml" Size="1735" LfhSize="46"><Block Hash="YfTJ/jnT6SalLprZBTKehHnc52buekiRfwgoV8Htzko=" Size="729"/></File></BlockMap>