{
  "appInfo" : {
    "build" : "222.3739.54",
    "buildDate" : "2022-08-16T05:01:41.041Z[UTC]",
    "productCode" : "IC",
    "generated" : "2023-03-02T09:42:55.7238124Z",
    "os" : "Windows 11 10.0",
    "runtime" : "JetBrains s.r.o. 17.0.3 17.0.3+7-b469.37"
  },
  "runtimeInfo" : {
    "maxMemory" : 2136997888,
    "numberOfProcessors" : 8,
    "maxNumberOfIndexingThreads" : 4,
    "maxSizeOfFileForIntelliSense" : 2560000,
    "maxSizeOfFileForContentLoading" : 20971520
  },
  "projectIndexingHistory" : {
    "projectName" : "EmployManagementSystem (3).java",
    "times" : {
      "indexingReason" : "On refresh of 11 files",
      "scanningType" : "REFRESH",
      "totalUpdatingTime" : 138928800,
      "indexingTime" : 140593400,
      "contentLoadingVisibleTime" : 1123454,
      "creatingIteratorsTime" : 0,
      "scanFilesTime" : 80400,
      "pushPropertiesTime" : 0,
      "indexExtensionsTime" : 0,
      "isAppliedAllValuesSeparately" : true,
      "separateApplyingIndexesVisibleTime" : 3996640,
      "updatingStart" : "2023-03-02T09:42:55.583219Z",
      "updatingEnd" : "2023-03-02T09:42:55.7238124Z",
      "totalSuspendedTime" : 0,
      "wasInterrupted" : false
    },
    "fileCount" : {
      "numberOfFileProviders" : 1,
      "numberOfScannedFiles" : 11,
      "numberOfFilesIndexedByInfrastructureExtensionsDuringScan" : 0,
      "numberOfFilesScheduledForIndexingAfterScan" : 11,
      "numberOfFilesIndexedByInfrastructureExtensionsDuringIndexingStage" : 0,
      "numberOfFilesIndexedWithLoadingContent" : 10
    },
    "totalStatsPerFileType" : [ {
      "fileType" : "HTML",
      "partOfTotalProcessingTime" : {
        "part" : 253843400,
        "total" : 343804303
      },
      "partOfTotalContentLoadingTime" : {
        "part" : 1180100,
        "total" : 2784799
      },
      "totalNumberOfFiles" : 3,
      "totalFilesSize" : 126412,
      "indexingSpeed" : {
        "totalBytes" : 126412,
        "totalTime" : 253843400
      },
      "biggestContributors" : [ {
        "providerName" : "Refreshed files",
        "numberOfFiles" : 3,
        "totalFilesSize" : 126412,
        "partOfTotalProcessingTimeOfThisFileType" : {
          "part" : 253843400,
          "total" : 253843400
        }
      } ]
    }, {
      "fileType" : "JSON",
      "partOfTotalProcessingTime" : {
        "part" : 42405202,
        "total" : 343804303
      },
      "partOfTotalContentLoadingTime" : {
        "part" : 1000501,
        "total" : 2784799
      },
      "totalNumberOfFiles" : 4,
      "totalFilesSize" : 64986,
      "indexingSpeed" : {
        "totalBytes" : 64986,
        "totalTime" : 42405202
      },
      "biggestContributors" : [ {
        "providerName" : "Refreshed files",
        "numberOfFiles" : 4,
        "totalFilesSize" : 64986,
        "partOfTotalProcessingTimeOfThisFileType" : {
          "part" : 42405202,
          "total" : 42405202
        }
      } ]
    }, {
      "fileType" : "XML",
      "partOfTotalProcessingTime" : {
        "part" : 35603001,
        "total" : 343804303
      },
      "partOfTotalContentLoadingTime" : {
        "part" : 559000,
        "total" : 2784799
      },
      "totalNumberOfFiles" : 1,
      "totalFilesSize" : 5198,
      "indexingSpeed" : {
        "totalBytes" : 5198,
        "totalTime" : 35603001
      },
      "biggestContributors" : [ {
        "providerName" : "Refreshed files",
        "numberOfFiles" : 1,
        "totalFilesSize" : 5198,
        "partOfTotalProcessingTimeOfThisFileType" : {
          "part" : 35603001,
          "total" : 35603001
        }
      } ]
    }, {
      "fileType" : "UNKNOWN",
      "partOfTotalProcessingTime" : {
        "part" : 11952700,
        "total" : 343804303
      },
      "partOfTotalContentLoadingTime" : {
        "part" : 45198,
        "total" : 2784799
      },
      "totalNumberOfFiles" : 2,
      "totalFilesSize" : 0,
      "indexingSpeed" : {
        "totalBytes" : 0,
        "totalTime" : 11952700
      },
      "biggestContributors" : [ {
        "providerName" : "Refreshed files",
        "numberOfFiles" : 2,
        "totalFilesSize" : 0,
        "partOfTotalProcessingTimeOfThisFileType" : {
          "part" : 11952700,
          "total" : 11952700
        }
      } ]
    } ],
    "totalStatsPerIndexer" : [ {
      "indexId" : "Stubs",
      "partOfTotalIndexingTime" : {
        "part" : 105278300,
        "total" : 229035900
      },
      "totalNumberOfFiles" : 4,
      "totalNumberOfFilesIndexedByExtensions" : 0,
      "totalFilesSize" : 131610,
      "indexingSpeed" : {
        "totalBytes" : 131610,
        "totalTime" : 105278300
      },
      "snapshotInputMappingStats" : {
        "totalRequests" : 0,
        "totalMisses" : 0,
        "totalHits" : 0
      }
    }, {
      "indexId" : "IdIndex",
      "partOfTotalIndexingTime" : {
        "part" : 94040097,
        "total" : 229035900
      },
      "totalNumberOfFiles" : 8,
      "totalNumberOfFilesIndexedByExtensions" : 0,
      "totalFilesSize" : 196596,
      "indexingSpeed" : {
        "totalBytes" : 196596,
        "totalTime" : 94040097
      },
      "snapshotInputMappingStats" : {
        "totalRequests" : 0,
        "totalMisses" : 0,
        "totalHits" : 0
      }
    }, {
      "indexId" : "html5.custom.attributes.index",
      "partOfTotalIndexingTime" : {
        "part" : 21305399,
        "total" : 229035900
      },
      "totalNumberOfFiles" : 3,
      "totalNumberOfFilesIndexedByExtensions" : 0,
      "totalFilesSize" : 126412,
      "indexingSpeed" : {
        "totalBytes" : 126412,
        "totalTime" : 21305399
      },
      "snapshotInputMappingStats" : {
        "totalRequests" : 0,
        "totalMisses" : 0,
        "totalHits" : 0
      }
    }, {
      "indexId" : "Trigram.Index",
      "partOfTotalIndexingTime" : {
        "part" : 4823902,
        "total" : 229035900
      },
      "totalNumberOfFiles" : 8,
      "totalNumberOfFilesIndexedByExtensions" : 0,
      "totalFilesSize" : 196596,
      "indexingSpeed" : {
        "totalBytes" : 196596,
        "totalTime" : 4823902
      },
      "snapshotInputMappingStats" : {
        "totalRequests" : 0,
        "totalMisses" : 0,
        "totalHits" : 0
      }
    }, {
      "indexId" : "json.file.root.values",
      "partOfTotalIndexingTime" : {
        "part" : 1887401,
        "total" : 229035900
      },
      "totalNumberOfFiles" : 4,
      "totalNumberOfFilesIndexedByExtensions" : 0,
      "totalFilesSize" : 64986,
      "indexingSpeed" : {
        "totalBytes" : 64986,
        "totalTime" : 1887401
      },
      "snapshotInputMappingStats" : {
        "totalRequests" : 0,
        "totalMisses" : 0,
        "totalHits" : 0
      }
    }, {
      "indexId" : "ant-imports",
      "partOfTotalIndexingTime" : {
        "part" : 964701,
        "total" : 229035900
      },
      "totalNumberOfFiles" : 1,
      "totalNumberOfFilesIndexedByExtensions" : 0,
      "totalFilesSize" : 5198,
      "indexingSpeed" : {
        "totalBytes" : 5198,
        "totalTime" : 964701
      },
      "snapshotInputMappingStats" : {
        "totalRequests" : 0,
        "totalMisses" : 0,
        "totalHits" : 0
      }
    }, {
      "indexId" : "fileIncludes",
      "partOfTotalIndexingTime" : {
        "part" : 298600,
        "total" : 229035900
      },
      "totalNumberOfFiles" : 1,
      "totalNumberOfFilesIndexedByExtensions" : 0,
      "totalFilesSize" : 5198,
      "indexingSpeed" : {
        "totalBytes" : 5198,
        "totalTime" : 298600
      },
      "snapshotInputMappingStats" : {
        "totalRequests" : 0,
        "totalMisses" : 0,
        "totalHits" : 0
      }
    }, {
      "indexId" : "DomFileIndex",
      "partOfTotalIndexingTime" : {
        "part" : 145700,
        "total" : 229035900
      },
      "totalNumberOfFiles" : 1,
      "totalNumberOfFilesIndexedByExtensions" : 0,
      "totalFilesSize" : 5198,
      "indexingSpeed" : {
        "totalBytes" : 5198,
        "totalTime" : 145700
      },
      "snapshotInputMappingStats" : {
        "totalRequests" : 0,
        "totalMisses" : 0,
        "totalHits" : 0
      }
    }, {
      "indexId" : "RelaxSymbolIndex",
      "partOfTotalIndexingTime" : {
        "part" : 85301,
        "total" : 229035900
      },
      "totalNumberOfFiles" : 1,
      "totalNumberOfFilesIndexedByExtensions" : 0,
      "totalFilesSize" : 5198,
      "indexingSpeed" : {
        "totalBytes" : 5198,
        "totalTime" : 85301
      },
      "snapshotInputMappingStats" : {
        "totalRequests" : 0,
        "totalMisses" : 0,
        "totalHits" : 0
      }
    }, {
      "indexId" : "XsltSymbolIndex",
      "partOfTotalIndexingTime" : {
        "part" : 85200,
        "total" : 229035900
      },
      "totalNumberOfFiles" : 1,
      "totalNumberOfFilesIndexedByExtensions" : 0,
      "totalFilesSize" : 5198,
      "indexingSpeed" : {
        "totalBytes" : 5198,
        "totalTime" : 85200
      },
      "snapshotInputMappingStats" : {
        "totalRequests" : 0,
        "totalMisses" : 0,
        "totalHits" : 0
      }
    }, {
      "indexId" : "xmlProperties",
      "partOfTotalIndexingTime" : {
        "part" : 84399,
        "total" : 229035900
      },
      "totalNumberOfFiles" : 1,
      "totalNumberOfFilesIndexedByExtensions" : 0,
      "totalFilesSize" : 5198,
      "indexingSpeed" : {
        "totalBytes" : 5198,
        "totalTime" : 84399
      },
      "snapshotInputMappingStats" : {
        "totalRequests" : 0,
        "totalMisses" : 0,
        "totalHits" : 0
      }
    }, {
      "indexId" : "FrameworkDetectionIndex",
      "partOfTotalIndexingTime" : {
        "part" : 31901,
        "total" : 229035900
      },
      "totalNumberOfFiles" : 1,
      "totalNumberOfFilesIndexedByExtensions" : 0,
      "totalFilesSize" : 5198,
      "indexingSpeed" : {
        "totalBytes" : 5198,
        "totalTime" : 31901
      },
      "snapshotInputMappingStats" : {
        "totalRequests" : 0,
        "totalMisses" : 0,
        "totalHits" : 0
      }
    }, {
      "indexId" : "IdeaPluginRegistrationIndex",
      "partOfTotalIndexingTime" : {
        "part" : 1600,
        "total" : 229035900
      },
      "totalNumberOfFiles" : 1,
      "totalNumberOfFilesIndexedByExtensions" : 0,
      "totalFilesSize" : 5198,
      "indexingSpeed" : {
        "totalBytes" : 5198,
        "totalTime" : 1600
      },
      "snapshotInputMappingStats" : {
        "totalRequests" : 0,
        "totalMisses" : 0,
        "totalHits" : 0
      }
    }, {
      "indexId" : "PluginIdDependenciesIndex",
      "partOfTotalIndexingTime" : {
        "part" : 1099,
        "total" : 229035900
      },
      "totalNumberOfFiles" : 1,
      "totalNumberOfFilesIndexedByExtensions" : 0,
      "totalFilesSize" : 5198,
      "indexingSpeed" : {
        "totalBytes" : 5198,
        "totalTime" : 1099
      },
      "snapshotInputMappingStats" : {
        "totalRequests" : 0,
        "totalMisses" : 0,
        "totalHits" : 0
      }
    }, {
      "indexId" : "PluginIdModuleIndex",
      "partOfTotalIndexingTime" : {
        "part" : 900,
        "total" : 229035900
      },
      "totalNumberOfFiles" : 1,
      "totalNumberOfFilesIndexedByExtensions" : 0,
      "totalFilesSize" : 5198,
      "indexingSpeed" : {
        "totalBytes" : 5198,
        "totalTime" : 900
      },
      "snapshotInputMappingStats" : {
        "totalRequests" : 0,
        "totalMisses" : 0,
        "totalHits" : 0
      }
    }, {
      "indexId" : "devkit.ExtensionPointClassIndex",
      "partOfTotalIndexingTime" : {
        "part" : 700,
        "total" : 229035900
      },
      "totalNumberOfFiles" : 1,
      "totalNumberOfFilesIndexedByExtensions" : 0,
      "totalFilesSize" : 5198,
      "indexingSpeed" : {
        "totalBytes" : 5198,
        "totalTime" : 700
      },
      "snapshotInputMappingStats" : {
        "totalRequests" : 0,
        "totalMisses" : 0,
        "totalHits" : 0
      }
    }, {
      "indexId" : "devkit.ExtensionPointIndex",
      "partOfTotalIndexingTime" : {
        "part" : 700,
        "total" : 229035900
      },
      "totalNumberOfFiles" : 1,
      "totalNumberOfFilesIndexedByExtensions" : 0,
      "totalFilesSize" : 5198,
      "indexingSpeed" : {
        "totalBytes" : 5198,
        "totalTime" : 700
      },
      "snapshotInputMappingStats" : {
        "totalRequests" : 0,
        "totalMisses" : 0,
        "totalHits" : 0
      }
    } ],
    "scanningStatistics" : [ {
      "providerName" : "Refreshed files",
      "numberOfScannedFiles" : 11,
      "numberOfSkippedFiles" : 0,
      "numberOfFilesForIndexing" : 11,
      "numberOfFilesFullyIndexedByInfrastructureExtensions" : 0,
      "filesFullyIndexedByInfrastructureExtensions" : [ ],
      "statusTime" : 0,
      "scanningTime" : 80400,
      "timeProcessingUpToDateFiles" : 0,
      "timeUpdatingContentLessIndexes" : 0,
      "timeIndexingWithoutContent" : 0,
      "roots" : [ "Not collected for refresh" ]
    } ],
    "fileProviderStatistics" : [ {
      "providerName" : "Refreshed files",
      "totalNumberOfIndexedFiles" : 10,
      "totalNumberOfFilesFullyIndexedByExtensions" : 0,
      "totalIndexingVisibleTime" : 138698900,
      "contentLoadingVisibleTime" : 1123454,
      "numberOfTooLargeForIndexingFiles" : 0,
      "slowIndexedFiles" : [ ],
      "filesFullyIndexedByExtensions" : [ ],
      "isAppliedAllValuesSeparately" : true,
      "separateApplyingIndexesVisibleTime" : 3996640
    } ],
    "visibleTimeToAllThreadTimeRatio" : 0.40342397925135914
  }
}