{
  "appInfo" : {
    "build" : "222.3739.54",
    "buildDate" : "2022-08-16T05:01:41.041Z[UTC]",
    "productCode" : "IC",
    "generated" : "2023-03-02T08:27:28.5821602Z",
    "os" : "Windows 11 10.0",
    "runtime" : "JetBrains s.r.o. 17.0.3 17.0.3+7-b469.37"
  },
  "runtimeInfo" : {
    "maxMemory" : 2136997888,
    "numberOfProcessors" : 8,
    "maxNumberOfIndexingThreads" : 4,
    "maxSizeOfFileForIntelliSense" : 2560000,
    "maxSizeOfFileForContentLoading" : 20971520
  },
  "projectIndexingHistory" : {
    "projectName" : "EmployManagementSystem (3).java",
    "times" : {
      "indexingReason" : "On refresh of 6 files",
      "scanningType" : "REFRESH",
      "totalUpdatingTime" : 46110000,
      "indexingTime" : 35358600,
      "contentLoadingVisibleTime" : 320563,
      "creatingIteratorsTime" : 0,
      "scanFilesTime" : 40900,
      "pushPropertiesTime" : 0,
      "indexExtensionsTime" : 0,
      "isAppliedAllValuesSeparately" : true,
      "separateApplyingIndexesVisibleTime" : 913678,
      "updatingStart" : "2023-03-02T08:27:28.5468016Z",
      "updatingEnd" : "2023-03-02T08:27:28.5821602Z",
      "totalSuspendedTime" : 0,
      "wasInterrupted" : false
    },
    "fileCount" : {
      "numberOfFileProviders" : 1,
      "numberOfScannedFiles" : 6,
      "numberOfFilesIndexedByInfrastructureExtensionsDuringScan" : 0,
      "numberOfFilesScheduledForIndexingAfterScan" : 6,
      "numberOfFilesIndexedByInfrastructureExtensionsDuringIndexingStage" : 0,
      "numberOfFilesIndexedWithLoadingContent" : 5
    },
    "totalStatsPerFileType" : [ {
      "fileType" : "HTML",
      "partOfTotalProcessingTime" : {
        "part" : 85413100,
        "total" : 151768400
      },
      "partOfTotalContentLoadingTime" : {
        "part" : 570100,
        "total" : 1058900
      },
      "totalNumberOfFiles" : 2,
      "totalFilesSize" : 64272,
      "indexingSpeed" : {
        "totalBytes" : 64272,
        "totalTime" : 85413100
      },
      "biggestContributors" : [ {
        "providerName" : "Refreshed files",
        "numberOfFiles" : 2,
        "totalFilesSize" : 64272,
        "partOfTotalProcessingTimeOfThisFileType" : {
          "part" : 85413100,
          "total" : 85413100
        }
      } ]
    }, {
      "fileType" : "JSON",
      "partOfTotalProcessingTime" : {
        "part" : 66355300,
        "total" : 151768400
      },
      "partOfTotalContentLoadingTime" : {
        "part" : 488800,
        "total" : 1058900
      },
      "totalNumberOfFiles" : 3,
      "totalFilesSize" : 32656,
      "indexingSpeed" : {
        "totalBytes" : 32656,
        "totalTime" : 66355300
      },
      "biggestContributors" : [ {
        "providerName" : "Refreshed files",
        "numberOfFiles" : 3,
        "totalFilesSize" : 32656,
        "partOfTotalProcessingTimeOfThisFileType" : {
          "part" : 66355300,
          "total" : 66355300
        }
      } ]
    } ],
    "totalStatsPerIndexer" : [ {
      "indexId" : "IdIndex",
      "partOfTotalIndexingTime" : {
        "part" : 55477200,
        "total" : 128916200
      },
      "totalNumberOfFiles" : 5,
      "totalNumberOfFilesIndexedByExtensions" : 0,
      "totalFilesSize" : 96928,
      "indexingSpeed" : {
        "totalBytes" : 96928,
        "totalTime" : 55477200
      },
      "snapshotInputMappingStats" : {
        "totalRequests" : 0,
        "totalMisses" : 0,
        "totalHits" : 0
      }
    }, {
      "indexId" : "html5.custom.attributes.index",
      "partOfTotalIndexingTime" : {
        "part" : 52527600,
        "total" : 128916200
      },
      "totalNumberOfFiles" : 2,
      "totalNumberOfFilesIndexedByExtensions" : 0,
      "totalFilesSize" : 64272,
      "indexingSpeed" : {
        "totalBytes" : 64272,
        "totalTime" : 52527600
      },
      "snapshotInputMappingStats" : {
        "totalRequests" : 0,
        "totalMisses" : 0,
        "totalHits" : 0
      }
    }, {
      "indexId" : "Stubs",
      "partOfTotalIndexingTime" : {
        "part" : 18135700,
        "total" : 128916200
      },
      "totalNumberOfFiles" : 2,
      "totalNumberOfFilesIndexedByExtensions" : 0,
      "totalFilesSize" : 64272,
      "indexingSpeed" : {
        "totalBytes" : 64272,
        "totalTime" : 18135700
      },
      "snapshotInputMappingStats" : {
        "totalRequests" : 0,
        "totalMisses" : 0,
        "totalHits" : 0
      }
    }, {
      "indexId" : "Trigram.Index",
      "partOfTotalIndexingTime" : {
        "part" : 2184000,
        "total" : 128916200
      },
      "totalNumberOfFiles" : 5,
      "totalNumberOfFilesIndexedByExtensions" : 0,
      "totalFilesSize" : 96928,
      "indexingSpeed" : {
        "totalBytes" : 96928,
        "totalTime" : 2184000
      },
      "snapshotInputMappingStats" : {
        "totalRequests" : 0,
        "totalMisses" : 0,
        "totalHits" : 0
      }
    }, {
      "indexId" : "json.file.root.values",
      "partOfTotalIndexingTime" : {
        "part" : 591700,
        "total" : 128916200
      },
      "totalNumberOfFiles" : 3,
      "totalNumberOfFilesIndexedByExtensions" : 0,
      "totalFilesSize" : 32656,
      "indexingSpeed" : {
        "totalBytes" : 32656,
        "totalTime" : 591700
      },
      "snapshotInputMappingStats" : {
        "totalRequests" : 0,
        "totalMisses" : 0,
        "totalHits" : 0
      }
    } ],
    "scanningStatistics" : [ {
      "providerName" : "Refreshed files",
      "numberOfScannedFiles" : 6,
      "numberOfSkippedFiles" : 0,
      "numberOfFilesForIndexing" : 6,
      "numberOfFilesFullyIndexedByInfrastructureExtensions" : 0,
      "filesFullyIndexedByInfrastructureExtensions" : [ ],
      "statusTime" : 0,
      "scanningTime" : 40900,
      "timeProcessingUpToDateFiles" : 0,
      "timeUpdatingContentLessIndexes" : 0,
      "timeIndexingWithoutContent" : 0,
      "roots" : [ "Not collected for refresh" ]
    } ],
    "fileProviderStatistics" : [ {
      "providerName" : "Refreshed files",
      "totalNumberOfIndexedFiles" : 5,
      "totalNumberOfFilesFullyIndexedByExtensions" : 0,
      "totalIndexingVisibleTime" : 45945300,
      "contentLoadingVisibleTime" : 320563,
      "numberOfTooLargeForIndexingFiles" : 0,
      "slowIndexedFiles" : [ ],
      "filesFullyIndexedByExtensions" : [ ],
      "isAppliedAllValuesSeparately" : true,
      "separateApplyingIndexesVisibleTime" : 913678
    } ],
    "visibleTimeToAllThreadTimeRatio" : 0.302732979987929
  }
}