{
  "appInfo" : {
    "build" : "222.3739.54",
    "buildDate" : "2022-08-16T05:01:41.041Z[UTC]",
    "productCode" : "IC",
    "generated" : "2023-03-02T08:05:35.9182029Z",
    "os" : "Windows 11 10.0",
    "runtime" : "JetBrains s.r.o. 17.0.3 17.0.3+7-b469.37"
  },
  "runtimeInfo" : {
    "maxMemory" : 2136997888,
    "numberOfProcessors" : 8,
    "maxNumberOfIndexingThreads" : 4,
    "maxSizeOfFileForIntelliSense" : 2560000,
    "maxSizeOfFileForContentLoading" : 20971520
  },
  "projectIndexingHistory" : {
    "projectName" : "EmployManagementSystem (3).java",
    "times" : {
      "indexingReason" : "On refresh of 9 files",
      "scanningType" : "REFRESH",
      "totalUpdatingTime" : 104421800,
      "indexingTime" : 88784500,
      "contentLoadingVisibleTime" : 1184849,
      "creatingIteratorsTime" : 0,
      "scanFilesTime" : 174100,
      "pushPropertiesTime" : 0,
      "indexExtensionsTime" : 0,
      "isAppliedAllValuesSeparately" : true,
      "separateApplyingIndexesVisibleTime" : 8749365,
      "updatingStart" : "2023-03-02T08:05:35.8127971Z",
      "updatingEnd" : "2023-03-02T08:05:35.9025781Z",
      "totalSuspendedTime" : 0,
      "wasInterrupted" : false
    },
    "fileCount" : {
      "numberOfFileProviders" : 1,
      "numberOfScannedFiles" : 9,
      "numberOfFilesIndexedByInfrastructureExtensionsDuringScan" : 0,
      "numberOfFilesScheduledForIndexingAfterScan" : 9,
      "numberOfFilesIndexedByInfrastructureExtensionsDuringIndexingStage" : 0,
      "numberOfFilesIndexedWithLoadingContent" : 8
    },
    "totalStatsPerFileType" : [ {
      "fileType" : "HTML",
      "partOfTotalProcessingTime" : {
        "part" : 153802100,
        "total" : 347874100
      },
      "partOfTotalContentLoadingTime" : {
        "part" : 598700,
        "total" : 3966500
      },
      "totalNumberOfFiles" : 2,
      "totalFilesSize" : 44378,
      "indexingSpeed" : {
        "totalBytes" : 44378,
        "totalTime" : 153802100
      },
      "biggestContributors" : [ {
        "providerName" : "Refreshed files",
        "numberOfFiles" : 2,
        "totalFilesSize" : 44378,
        "partOfTotalProcessingTimeOfThisFileType" : {
          "part" : 153802100,
          "total" : 153802100
        }
      } ]
    }, {
      "fileType" : "PLAIN_TEXT",
      "partOfTotalProcessingTime" : {
        "part" : 138211200,
        "total" : 347874100
      },
      "partOfTotalContentLoadingTime" : {
        "part" : 1145000,
        "total" : 3966500
      },
      "totalNumberOfFiles" : 2,
      "totalFilesSize" : 1219509,
      "indexingSpeed" : {
        "totalBytes" : 1219509,
        "totalTime" : 138211200
      },
      "biggestContributors" : [ {
        "providerName" : "Refreshed files",
        "numberOfFiles" : 2,
        "totalFilesSize" : 1219509,
        "partOfTotalProcessingTimeOfThisFileType" : {
          "part" : 138211200,
          "total" : 138211200
        }
      } ]
    }, {
      "fileType" : "JSON",
      "partOfTotalProcessingTime" : {
        "part" : 46308000,
        "total" : 347874100
      },
      "partOfTotalContentLoadingTime" : {
        "part" : 2185100,
        "total" : 3966500
      },
      "totalNumberOfFiles" : 3,
      "totalFilesSize" : 23217,
      "indexingSpeed" : {
        "totalBytes" : 23217,
        "totalTime" : 46308000
      },
      "biggestContributors" : [ {
        "providerName" : "Refreshed files",
        "numberOfFiles" : 3,
        "totalFilesSize" : 23217,
        "partOfTotalProcessingTimeOfThisFileType" : {
          "part" : 46308000,
          "total" : 46308000
        }
      } ]
    }, {
      "fileType" : "UNKNOWN",
      "partOfTotalProcessingTime" : {
        "part" : 9552800,
        "total" : 347874100
      },
      "partOfTotalContentLoadingTime" : {
        "part" : 37700,
        "total" : 3966500
      },
      "totalNumberOfFiles" : 1,
      "totalFilesSize" : 0,
      "indexingSpeed" : {
        "totalBytes" : 0,
        "totalTime" : 9552800
      },
      "biggestContributors" : [ {
        "providerName" : "Refreshed files",
        "numberOfFiles" : 1,
        "totalFilesSize" : 0,
        "partOfTotalProcessingTimeOfThisFileType" : {
          "part" : 9552800,
          "total" : 9552800
        }
      } ]
    } ],
    "totalStatsPerIndexer" : [ {
      "indexId" : "Stubs",
      "partOfTotalIndexingTime" : {
        "part" : 48227000,
        "total" : 120603900
      },
      "totalNumberOfFiles" : 2,
      "totalNumberOfFilesIndexedByExtensions" : 0,
      "totalFilesSize" : 44378,
      "indexingSpeed" : {
        "totalBytes" : 44378,
        "totalTime" : 48227000
      },
      "snapshotInputMappingStats" : {
        "totalRequests" : 0,
        "totalMisses" : 0,
        "totalHits" : 0
      }
    }, {
      "indexId" : "IdIndex",
      "partOfTotalIndexingTime" : {
        "part" : 42750900,
        "total" : 120603900
      },
      "totalNumberOfFiles" : 7,
      "totalNumberOfFilesIndexedByExtensions" : 0,
      "totalFilesSize" : 1287104,
      "indexingSpeed" : {
        "totalBytes" : 1287104,
        "totalTime" : 42750900
      },
      "snapshotInputMappingStats" : {
        "totalRequests" : 0,
        "totalMisses" : 0,
        "totalHits" : 0
      }
    }, {
      "indexId" : "Trigram.Index",
      "partOfTotalIndexingTime" : {
        "part" : 23994100,
        "total" : 120603900
      },
      "totalNumberOfFiles" : 7,
      "totalNumberOfFilesIndexedByExtensions" : 0,
      "totalFilesSize" : 1287104,
      "indexingSpeed" : {
        "totalBytes" : 1287104,
        "totalTime" : 23994100
      },
      "snapshotInputMappingStats" : {
        "totalRequests" : 0,
        "totalMisses" : 0,
        "totalHits" : 0
      }
    }, {
      "indexId" : "html5.custom.attributes.index",
      "partOfTotalIndexingTime" : {
        "part" : 5191800,
        "total" : 120603900
      },
      "totalNumberOfFiles" : 2,
      "totalNumberOfFilesIndexedByExtensions" : 0,
      "totalFilesSize" : 44378,
      "indexingSpeed" : {
        "totalBytes" : 44378,
        "totalTime" : 5191800
      },
      "snapshotInputMappingStats" : {
        "totalRequests" : 0,
        "totalMisses" : 0,
        "totalHits" : 0
      }
    }, {
      "indexId" : "json.file.root.values",
      "partOfTotalIndexingTime" : {
        "part" : 440100,
        "total" : 120603900
      },
      "totalNumberOfFiles" : 3,
      "totalNumberOfFilesIndexedByExtensions" : 0,
      "totalFilesSize" : 23217,
      "indexingSpeed" : {
        "totalBytes" : 23217,
        "totalTime" : 440100
      },
      "snapshotInputMappingStats" : {
        "totalRequests" : 0,
        "totalMisses" : 0,
        "totalHits" : 0
      }
    } ],
    "scanningStatistics" : [ {
      "providerName" : "Refreshed files",
      "numberOfScannedFiles" : 9,
      "numberOfSkippedFiles" : 0,
      "numberOfFilesForIndexing" : 9,
      "numberOfFilesFullyIndexedByInfrastructureExtensions" : 0,
      "filesFullyIndexedByInfrastructureExtensions" : [ ],
      "statusTime" : 0,
      "scanningTime" : 174100,
      "timeProcessingUpToDateFiles" : 0,
      "timeUpdatingContentLessIndexes" : 0,
      "timeIndexingWithoutContent" : 0,
      "roots" : [ "Not collected for refresh" ]
    } ],
    "fileProviderStatistics" : [ {
      "providerName" : "Refreshed files",
      "totalNumberOfIndexedFiles" : 8,
      "totalNumberOfFilesFullyIndexedByExtensions" : 0,
      "totalIndexingVisibleTime" : 103914900,
      "contentLoadingVisibleTime" : 1184849,
      "numberOfTooLargeForIndexingFiles" : 0,
      "slowIndexedFiles" : [ ],
      "filesFullyIndexedByExtensions" : [ ],
      "isAppliedAllValuesSeparately" : true,
      "separateApplyingIndexesVisibleTime" : 8749365
    } ],
    "visibleTimeToAllThreadTimeRatio" : 0.2987141037519033
  }
}